<?xml version="1.0" encoding="ISO-8859-1"?>
	<ProgramGuide>
		<Service id="1000" name="Service Name">
			<Event id="1">
				<IdName>Fantozzi-GrandiMagazzini</IdName>
				<StartDate>2017-09-13</StartDate>
				<StartTime>18:41:57</StartTime>
				<EndDate>2017-09-13</EndDate>
				<EndTime>20:32:33</EndTime>
				<ShortEventDescription>
					<LanguageCode>ita</LanguageCode>
					<LanguageName>Italian</LanguageName>
					<Name>FANTOZZI GRANDI MAGAZZINI</Name>
					<Description>GRANDI MAGAZZINI</Description>
				</ShortEventDescription>
			</Event>
			<Event id="2">
				<IdName>7PROMOVIDEOspot7</IdName>
				<StartDate>2017-09-13</StartDate>
				<StartTime>20:32:33</StartTime>
				<EndDate>2017-09-13</EndDate>
				<EndTime>20:32:40</EndTime>
				<ShortEventDescription>
					<LanguageCode>ita</LanguageCode>
					<LanguageName>Italian</LanguageName>
					<Name>SPOT  PROMOVIDEOTV</Name>
					<Description>SPOT PROMOVIDEOTV</Description>
				</ShortEventDescription>
			</Event>
			<Event id="3">
				<IdName>Filmato</IdName>
				<StartDate>2017-09-13</StartDate>
				<StartTime>20:32:40</StartTime>
				<EndDate>2017-09-13</EndDate>
				<EndTime>20:35:10</EndTime>
				<ShortEventDescription>
					<LanguageCode>ita</LanguageCode>
					<LanguageName>Italian</LanguageName>
					<Name>GERACE IN 2 MINUTI</Name>
					<Description>GERACE</Description>
				</ShortEventDescription>
			</Event>
			<Event id="4">
				<IdName>7PROMOVIDEOspot7</IdName>
				<StartDate>2017-09-13</StartDate>
				<StartTime>20:35:10</StartTime>
				<EndDate>2017-09-13</EndDate>
				<EndTime>20:35:16</EndTime>
				<ShortEventDescription>
					<LanguageCode>ita</LanguageCode>
					<LanguageName>Italian</LanguageName>
					<Name>SPOT  PROMOVIDEOTV</Name>
					<Description>SPOT PROMOVIDEOTV</Description>
				</ShortEventDescription>
			</Event>
			<Event id="5">
				<IdName>minispotapplicazione</IdName>
				<StartDate>2017-09-13</StartDate>
				<StartTime>20:35:16</StartTime>
				<EndDate>2017-09-13</EndDate>
				<EndTime>20:35:27</EndTime>
				<ShortEventDescription>
					<LanguageCode>ita</LanguageCode>
					<LanguageName>Italian</LanguageName>
					<Name>SPOTAPP</Name>
					<Description>SPOTAPP</Description>
				</ShortEventDescription>
			</Event>
			<Event id="6">
				<IdName>6PROMOVIDEOSPOT6</IdName>
				<StartDate>2017-09-13</StartDate>
				<StartTime>20:35:27</StartTime>
				<EndDate>2017-09-13</EndDate>
				<EndTime>20:35:34</EndTime>
				<ShortEventDescription>
					<LanguageCode>ita</LanguageCode>
					<LanguageName>Italian</LanguageName>
					<Name>6 SPOT PTOMOVIDEO</Name>
					<Description>PROMOVIDEOSPOT 6</Description>
				</ShortEventDescription>
			</Event>
			<Event id="7">
				<IdName>Bellezzesullaspiaggia_mpeg2video</IdName>
				<StartDate>2017-09-13</StartDate>
				<StartTime>20:35:34</StartTime>
				<EndDate>2017-09-13</EndDate>
				<EndTime>21:58:43</EndTime>
				<ShortEventDescription>
					<LanguageCode>ita</LanguageCode>
					<LanguageName>Italian</LanguageName>
					<Name>Sconosciuto</Name>
					<Description>BELLEZZE SULLA SPIAGGIA</Description>
				</ShortEventDescription>
			</Event>
			<Event id="8">
				<IdName>AnimaliSerpentiFascinoLetale(Ita)</IdName>
				<StartDate>2017-09-13</StartDate>
				<StartTime>21:58:43</StartTime>
				<EndDate>2017-09-13</EndDate>
				<EndTime>22:50:48</EndTime>
				<ShortEventDescription>
					<LanguageCode>ita</LanguageCode>
					<LanguageName>Italian</LanguageName>
					<Name>ANIMALI SERPENTI</Name>
					<Description>ANIMALI SERPENTI</Description>
				</ShortEventDescription>
			</Event>
			<Event id="9">
				<IdName>spotDIGIII</IdName>
				<StartDate>2017-09-13</StartDate>
				<StartTime>22:50:48</StartTime>
				<EndDate>2017-09-13</EndDate>
				<EndTime>22:51:04</EndTime>
				<ShortEventDescription>
					<LanguageCode>ita</LanguageCode>
					<LanguageName>Italian</LanguageName>
					<Name>SPOT DIGII</Name>
					<Description>SPOT PROMOVIDEO</Description>
				</ShortEventDescription>
			</Event>
			<Event id="10">
				<IdName>PiedoneL'Africano</IdName>
				<StartDate>2017-09-13</StartDate>
				<StartTime>22:51:04</StartTime>
				<EndDate>2017-09-14</EndDate>
				<EndTime>00:39:59</EndTime>
				<ShortEventDescription>
					<LanguageCode>ita</LanguageCode>
					<LanguageName>Italian</LanguageName>
					<Name>Sconosciuto</Name>
					<Description>Piedone l' Africano</Description>
				</ShortEventDescription>
			</Event>
			<Event id="11">
				<IdName>Roma.drogata.la.polizia.non_.puo.intervenire.19751°t.</IdName>
				<StartDate>2017-09-14</StartDate>
				<StartTime>00:39:59</StartTime>
				<EndDate>2017-09-14</EndDate>
				<EndTime>01:28:19</EndTime>
				<ShortEventDescription>
					<LanguageCode>ita</LanguageCode>
					<LanguageName>Italian</LanguageName>
					<Name>ROMA DROGATA 1^</Name>
					<Description>ROMA DROGATA 1^</Description>
				</ShortEventDescription>
			</Event>
			<Event id="12">
				<IdName>Roma.drogata.la.polizia.non_.puo.intervenire.19752°t.</IdName>
				<StartDate>2017-09-14</StartDate>
				<StartTime>01:28:19</StartTime>
				<EndDate>2017-09-14</EndDate>
				<EndTime>02:09:33</EndTime>
				<ShortEventDescription>
					<LanguageCode>ita</LanguageCode>
					<LanguageName>Italian</LanguageName>
					<Name>ROMA DROGATA 2^</Name>
					<Description>ROMA DROGATA 2^</Description>
				</ShortEventDescription>
			</Event>
			<Event id="13">
				<IdName>Crash.Contatto.Fisico.2004.iTALiAN.MD.DVDRip.XviD-SiLENT</IdName>
				<StartDate>2017-09-14</StartDate>
				<StartTime>02:09:33</StartTime>
				<EndDate>2017-09-14</EndDate>
				<EndTime>03:58:05</EndTime>
				<ShortEventDescription>
					<LanguageCode>ita</LanguageCode>
					<LanguageName>Italian</LanguageName>
					<Name>CRASH CONTATTO   FINALE FISICO</Name>
					<Description>CRASH CONTATTO  FINALE</Description>
				</ShortEventDescription>
			</Event>
			<Event id="14">
				<IdName>Iscrivitialnostrocanalepromovideotvsuyoutube</IdName>
				<StartDate>2017-09-14</StartDate>
				<StartTime>03:58:05</StartTime>
				<EndDate>2017-09-14</EndDate>
				<EndTime>03:58:20</EndTime>
				<ShortEventDescription>
					<LanguageCode>ita</LanguageCode>
					<LanguageName>Italian</LanguageName>
					<Name>ISCRIVITI CANALE YOU TUBE</Name>
					<Description>ISCRIVITI CANALE YOU TUBE</Description>
				</ShortEventDescription>
			</Event>
			<Event id="15">
				<IdName>7PROMOVIDEOspot7</IdName>
				<StartDate>2017-09-14</StartDate>
				<StartTime>03:58:20</StartTime>
				<EndDate>2017-09-14</EndDate>
				<EndTime>03:58:27</EndTime>
				<ShortEventDescription>
					<LanguageCode>ita</LanguageCode>
					<LanguageName>Italian</LanguageName>
					<Name>SPOT  PROMOVIDEOTV</Name>
					<Description>SPOT PROMOVIDEOTV</Description>
				</ShortEventDescription>
			</Event>
			<Event id="16">
				<IdName>IoStoConGliIppopotami</IdName>
				<StartDate>2017-09-14</StartDate>
				<StartTime>03:58:27</StartTime>
				<EndDate>2017-09-14</EndDate>
				<EndTime>05:42:53</EndTime>
				<ShortEventDescription>
					<LanguageCode>ita</LanguageCode>
					<LanguageName>Italian</LanguageName>
					<Name>Sconosciuto</Name>
					<Description>Io  sto  con gli Ippopotami</Description>
				</ShortEventDescription>
			</Event>
			<Event id="17">
				<IdName>_1779_Recanatese_Lunaametà</IdName>
				<StartDate>2017-09-14</StartDate>
				<StartTime>05:42:53</StartTime>
				<EndDate>2017-09-14</EndDate>
				<EndTime>05:51:10</EndTime>
				<ShortEventDescription>
					<LanguageCode>ita</LanguageCode>
					<LanguageName>Italian</LanguageName>
					<Name>RECANATESE 'LUNA A META'</Name>
					<Description>RECANATESE  LUNA A METa'</Description>
				</ShortEventDescription>
			</Event>
			<Event id="18">
				<IdName>Gerace</IdName>
				<StartDate>2017-09-14</StartDate>
				<StartTime>05:51:10</StartTime>
				<EndDate>2017-09-14</EndDate>
				<EndTime>05:57:11</EndTime>
				<ShortEventDescription>
					<LanguageCode>ita</LanguageCode>
					<LanguageName>Italian</LanguageName>
					<Name>GERACE</Name>
					<Description>GERACE</Description>
				</ShortEventDescription>
			</Event>
		</Service>
	</ProgramGuide>
