<?xml version="1.0" encoding="ISO-8859-1"?>
	<ProgramGuide>
		<Service id="1000" name="Service Name">
			<Event id="1">
				<IdName>Colpogrosso_mpeg2video</IdName>
				<StartDate>2017-11-07</StartDate>
				<StartTime>05:20:21</StartTime>
				<EndDate>2017-11-07</EndDate>
				<EndTime>07:22:31</EndTime>
				<ShortEventDescription>
					<LanguageCode>ita</LanguageCode>
					<LanguageName>Italian</LanguageName>
					<Name>Colpogrosso</Name>
					<Description>COLPO  GROSSO</Description>
				</ShortEventDescription>
			</Event>
			<Event id="2">
				<IdName>DonCamilloMonsignoremanontroppo</IdName>
				<StartDate>2017-11-07</StartDate>
				<StartTime>07:22:31</StartTime>
				<EndDate>2017-11-07</EndDate>
				<EndTime>09:15:57</EndTime>
				<ShortEventDescription>
					<LanguageCode>ita</LanguageCode>
					<LanguageName>Italian</LanguageName>
					<Name>DON CAMILLO   MONSIGNORE</Name>
					<Description>DON CAMILLO MONSIGNORE</Description>
				</ShortEventDescription>
			</Event>
		</Service>
	</ProgramGuide>
