<?xml version="1.0" encoding="ISO-8859-1"?>
	<ProgramGuide>
		<Service id="1000" name="Service Name">
			<Event id="1">
				<IdName>Raccontiromani_mpeg2video</IdName>
				<StartDate>2017-11-25</StartDate>
				<StartTime>17:10:56</StartTime>
				<EndDate>2017-11-25</EndDate>
				<EndTime>18:44:57</EndTime>
				<ShortEventDescription>
					<LanguageCode>ita</LanguageCode>
					<LanguageName>Italian</LanguageName>
					<Name>Sconosciuto</Name>
					<Description>Racconti  romani</Description>
				</ShortEventDescription>
			</Event>
			<Event id="2">
				<IdName>SerraSanBrunoPiccolaGrandeItalia</IdName>
				<StartDate>2017-11-25</StartDate>
				<StartTime>18:44:57</StartTime>
				<EndDate>2017-11-25</EndDate>
				<EndTime>19:05:56</EndTime>
				<ShortEventDescription>
					<LanguageCode>ita</LanguageCode>
					<LanguageName>Italian</LanguageName>
					<Name>Piccola Grande Italia</Name>
					<Description>SERRA S. BRUNO</Description>
				</ShortEventDescription>
			</Event>
			<Event id="3">
				<IdName>CassanoFestadelSantissimoCrocifisso</IdName>
				<StartDate>2017-11-25</StartDate>
				<StartTime>19:05:56</StartTime>
				<EndDate>2017-11-25</EndDate>
				<EndTime>19:35:39</EndTime>
				<ShortEventDescription>
					<LanguageCode>ita</LanguageCode>
					<LanguageName>Italian</LanguageName>
					<Name>Sconosciuto</Name>
					<Description>Nuovo File</Description>
				</ShortEventDescription>
			</Event>
			<Event id="4">
				<IdName>SPOTCIBRIO-PROMOVIDEOTVOK</IdName>
				<StartDate>2017-11-25</StartDate>
				<StartTime>19:35:39</StartTime>
				<EndDate>2017-11-25</EndDate>
				<EndTime>19:36:24</EndTime>
				<ShortEventDescription>
					<LanguageCode>ita</LanguageCode>
					<LanguageName>Italian</LanguageName>
					<Name>Sconosciuto</Name>
					<Description>Nuovo File</Description>
				</ShortEventDescription>
			</Event>
			<Event id="5">
				<IdName>3PROMOVIDEOSPOT3</IdName>
				<StartDate>2017-11-25</StartDate>
				<StartTime>19:36:24</StartTime>
				<EndDate>2017-11-25</EndDate>
				<EndTime>19:36:31</EndTime>
				<ShortEventDescription>
					<LanguageCode>ita</LanguageCode>
					<LanguageName>Italian</LanguageName>
					<Name>spot promovideotv</Name>
					<Description>SPOT PROMOVIDEOTV 3</Description>
				</ShortEventDescription>
			</Event>
			<Event id="6">
				<IdName>ReggioCalabriaPiccolaGrandeItalia</IdName>
				<StartDate>2017-11-25</StartDate>
				<StartTime>19:36:31</StartTime>
				<EndDate>2017-11-25</EndDate>
				<EndTime>19:58:43</EndTime>
				<ShortEventDescription>
					<LanguageCode>ita</LanguageCode>
					<LanguageName>Italian</LanguageName>
					<Name>Sconosciuto</Name>
					<Description>Reggio piccola grande Italia  </Description>
				</ShortEventDescription>
			</Event>
			<Event id="7">
				<IdName>FLASHPARTE6DOPOLE22,30</IdName>
				<StartDate>2017-11-25</StartDate>
				<StartTime>19:58:43</StartTime>
				<EndDate>2017-11-25</EndDate>
				<EndTime>20:03:49</EndTime>
				<ShortEventDescription>
					<LanguageCode>ita</LanguageCode>
					<LanguageName>Italian</LanguageName>
					<Name>Sconosciuto</Name>
					<Description>Nuovo File</Description>
				</ShortEventDescription>
			</Event>
			<Event id="8">
				<IdName>6PROMOVIDEOSPOT6</IdName>
				<StartDate>2017-11-25</StartDate>
				<StartTime>20:03:49</StartTime>
				<EndDate>2017-11-25</EndDate>
				<EndTime>20:03:56</EndTime>
				<ShortEventDescription>
					<LanguageCode>ita</LanguageCode>
					<LanguageName>Italian</LanguageName>
					<Name>6 SPOT PTOMOVIDEO</Name>
					<Description>PROMOVIDEOSPOT 6</Description>
				</ShortEventDescription>
			</Event>
			<Event id="9">
				<IdName>FLASHPARTE2NONTRASMETTEREDALLE16,00ALLE19,00</IdName>
				<StartDate>2017-11-25</StartDate>
				<StartTime>20:03:56</StartTime>
				<EndDate>2017-11-25</EndDate>
				<EndTime>20:09:09</EndTime>
				<ShortEventDescription>
					<LanguageCode>ita</LanguageCode>
					<LanguageName>Italian</LanguageName>
					<Name>Sconosciuto</Name>
					<Description>Nuovo File</Description>
				</ShortEventDescription>
			</Event>
			<Event id="10">
				<IdName>7PROMOVIDEOspot7</IdName>
				<StartDate>2017-11-25</StartDate>
				<StartTime>20:09:09</StartTime>
				<EndDate>2017-11-25</EndDate>
				<EndTime>20:09:16</EndTime>
				<ShortEventDescription>
					<LanguageCode>ita</LanguageCode>
					<LanguageName>Italian</LanguageName>
					<Name>SPOT  PROMOVIDEOTV</Name>
					<Description>SPOT PROMOVIDEOTV</Description>
				</ShortEventDescription>
			</Event>
			<Event id="11">
				<IdName>StarshipTroopers2-Glieroidellafederazione</IdName>
				<StartDate>2017-11-25</StartDate>
				<StartTime>20:09:16</StartTime>
				<EndDate>2017-11-25</EndDate>
				<EndTime>21:37:08</EndTime>
				<ShortEventDescription>
					<LanguageCode>ita</LanguageCode>
					<LanguageName>Italian</LanguageName>
					<Name>Sconosciuto</Name>
					<Description>Trooper 2</Description>
				</ShortEventDescription>
			</Event>
			<Event id="12">
				<IdName>Filmato</IdName>
				<StartDate>2017-11-25</StartDate>
				<StartTime>21:37:08</StartTime>
				<EndDate>2017-11-25</EndDate>
				<EndTime>21:39:38</EndTime>
				<ShortEventDescription>
					<LanguageCode>ita</LanguageCode>
					<LanguageName>Italian</LanguageName>
					<Name>GERACE IN 2 MINUTI</Name>
					<Description>GERACE</Description>
				</ShortEventDescription>
			</Event>
			<Event id="13">
				<IdName>7PROMOVIDEOspot7</IdName>
				<StartDate>2017-11-25</StartDate>
				<StartTime>21:39:38</StartTime>
				<EndDate>2017-11-25</EndDate>
				<EndTime>21:39:45</EndTime>
				<ShortEventDescription>
					<LanguageCode>ita</LanguageCode>
					<LanguageName>Italian</LanguageName>
					<Name>SPOT  PROMOVIDEOTV</Name>
					<Description>SPOT PROMOVIDEOTV</Description>
				</ShortEventDescription>
			</Event>
			<Event id="14">
				<IdName>minispotapplicazione</IdName>
				<StartDate>2017-11-25</StartDate>
				<StartTime>21:39:45</StartTime>
				<EndDate>2017-11-25</EndDate>
				<EndTime>21:39:56</EndTime>
				<ShortEventDescription>
					<LanguageCode>ita</LanguageCode>
					<LanguageName>Italian</LanguageName>
					<Name>SPOTAPP</Name>
					<Description>SPOTAPP</Description>
				</ShortEventDescription>
			</Event>
			<Event id="15">
				<IdName>6PROMOVIDEOSPOT6</IdName>
				<StartDate>2017-11-25</StartDate>
				<StartTime>21:39:56</StartTime>
				<EndDate>2017-11-25</EndDate>
				<EndTime>21:40:02</EndTime>
				<ShortEventDescription>
					<LanguageCode>ita</LanguageCode>
					<LanguageName>Italian</LanguageName>
					<Name>6 SPOT PTOMOVIDEO</Name>
					<Description>PROMOVIDEOSPOT 6</Description>
				</ShortEventDescription>
			</Event>
			<Event id="16">
				<IdName>Bellezzesullaspiaggia_mpeg2video</IdName>
				<StartDate>2017-11-25</StartDate>
				<StartTime>21:40:02</StartTime>
				<EndDate>2017-11-25</EndDate>
				<EndTime>23:03:11</EndTime>
				<ShortEventDescription>
					<LanguageCode>ita</LanguageCode>
					<LanguageName>Italian</LanguageName>
					<Name>Sconosciuto</Name>
					<Description>BELLEZZE SULLA SPIAGGIA</Description>
				</ShortEventDescription>
			</Event>
			<Event id="17">
				<IdName>AnimaliSerpentiFascinoLetale(Ita)</IdName>
				<StartDate>2017-11-25</StartDate>
				<StartTime>23:03:11</StartTime>
				<EndDate>2017-11-25</EndDate>
				<EndTime>23:55:17</EndTime>
				<ShortEventDescription>
					<LanguageCode>ita</LanguageCode>
					<LanguageName>Italian</LanguageName>
					<Name>ANIMALI SERPENTI</Name>
					<Description>ANIMALI SERPENTI</Description>
				</ShortEventDescription>
			</Event>
			<Event id="18">
				<IdName>Iscrivitialnostrocanalepromovideotvsuyoutube</IdName>
				<StartDate>2017-11-25</StartDate>
				<StartTime>23:55:17</StartTime>
				<EndDate>2017-11-25</EndDate>
				<EndTime>23:55:32</EndTime>
				<ShortEventDescription>
					<LanguageCode>ita</LanguageCode>
					<LanguageName>Italian</LanguageName>
					<Name>ISCRIVITI CANALE YOU TUBE</Name>
					<Description>ISCRIVITI CANALE YOU TUBE</Description>
				</ShortEventDescription>
			</Event>
			<Event id="19">
				<IdName>Colpogrosso_mpeg2video</IdName>
				<StartDate>2017-11-25</StartDate>
				<StartTime>23:55:32</StartTime>
				<EndDate>2017-11-26</EndDate>
				<EndTime>01:57:42</EndTime>
				<ShortEventDescription>
					<LanguageCode>ita</LanguageCode>
					<LanguageName>Italian</LanguageName>
					<Name>Colpogrosso</Name>
					<Description>COLPO  GROSSO</Description>
				</ShortEventDescription>
			</Event>
			<Event id="20">
				<IdName>7PROMOVIDEOspot7</IdName>
				<StartDate>2017-11-26</StartDate>
				<StartTime>01:57:42</StartTime>
				<EndDate>2017-11-26</EndDate>
				<EndTime>01:57:49</EndTime>
				<ShortEventDescription>
					<LanguageCode>ita</LanguageCode>
					<LanguageName>Italian</LanguageName>
					<Name>SPOT  PROMOVIDEOTV</Name>
					<Description>SPOT PROMOVIDEOTV</Description>
				</ShortEventDescription>
			</Event>
			<Event id="21">
				<IdName>Crash.Contatto.Fisico.2004.iTALiAN.MD.DVDRip.XviD-SiLENT</IdName>
				<StartDate>2017-11-26</StartDate>
				<StartTime>01:57:49</StartTime>
				<EndDate>2017-11-26</EndDate>
				<EndTime>03:46:20</EndTime>
				<ShortEventDescription>
					<LanguageCode>ita</LanguageCode>
					<LanguageName>Italian</LanguageName>
					<Name>CRASH CONTATTO   FINALE FISICO</Name>
					<Description>CRASH CONTATTO  FINALE</Description>
				</ShortEventDescription>
			</Event>
			<Event id="22">
				<IdName>Gerace</IdName>
				<StartDate>2017-11-26</StartDate>
				<StartTime>03:46:20</StartTime>
				<EndDate>2017-11-26</EndDate>
				<EndTime>03:52:21</EndTime>
				<ShortEventDescription>
					<LanguageCode>ita</LanguageCode>
					<LanguageName>Italian</LanguageName>
					<Name>GERACE</Name>
					<Description>GERACE</Description>
				</ShortEventDescription>
			</Event>
			<Event id="23">
				<IdName>CityofGhost_mpeg2video</IdName>
				<StartDate>2017-11-26</StartDate>
				<StartTime>03:52:21</StartTime>
				<EndDate>2017-11-26</EndDate>
				<EndTime>05:44:04</EndTime>
				<ShortEventDescription>
					<LanguageCode>ita</LanguageCode>
					<LanguageName>Italian</LanguageName>
					<Name>Sconosciuto</Name>
					<Description>CYTY OF GHOST</Description>
				</ShortEventDescription>
			</Event>
		</Service>
	</ProgramGuide>
