<?xml version="1.0" encoding="ISO-8859-1"?>
	<ProgramGuide>
		<Service id="1000" name="Service Name">
			<Event id="1">
				<IdName>LocriConcorsoNazCaciocavallo_mpeg2video</IdName>
				<StartDate>2018-03-11</StartDate>
				<StartTime>02:33:12</StartTime>
				<EndDate>2018-03-11</EndDate>
				<EndTime>05:01:13</EndTime>
				<ShortEventDescription>
					<LanguageCode>ita</LanguageCode>
					<LanguageName>Italian</LanguageName>
					<Name>Sconosciuto</Name>
					<Description>Nuovo File</Description>
				</ShortEventDescription>
			</Event>
			<Event id="2">
				<IdName>Pasqua-NoceraTerinese</IdName>
				<StartDate>2018-03-11</StartDate>
				<StartTime>05:01:13</StartTime>
				<EndDate>2018-03-11</EndDate>
				<EndTime>05:12:36</EndTime>
				<ShortEventDescription>
					<LanguageCode>ita</LanguageCode>
					<LanguageName>Italian</LanguageName>
					<Name>Pasqua Nocera Terinese</Name>
					<Description>Pasqua Nocera Terinese</Description>
				</ShortEventDescription>
			</Event>
		</Service>
	</ProgramGuide>
